<?xml version="1.0" encoding="UTF-8"?>
<beans xmlns="http://www.springframework.org/schema/beans" xmlns:xsi="http://www.w3.org/2001/XMLSchema-instance"
       xmlns:context="http://www.springframework.org/schema/context" xmlns:jee="http://www.springframework.org/schema/jee"
       xmlns:tx="http://www.springframework.org/schema/tx"
       xsi:schemaLocation="
    http://www.springframework.org/schema/beans http://www.springframework.org/schema/beans/spring-beans-2.5.xsd
    http://www.springframework.org/schema/context http://www.springframework.org/schema/context/spring-context-2.5.xsd
    http://www.springframework.org/schema/jee http://www.springframework.org/schema/jee/spring-jee-2.5.xsd
	http://www.springframework.org/schema/tx http://www.springframework.org/schema/tx/spring-tx-2.5.xsd">
	
	<bean id="placeholderConfig" class="org.springframework.beans.factory.config.PropertyPlaceholderConfigurer">
		<property name="locations">
			<list>
				<value>/WEB-INF/red5-web.properties</value>
			</list>
		</property>
	</bean>
	
	<bean id="authClientRegistry" class="org.red5.webapps.admin.client.AuthClientRegistry"/>

	<bean id="web.context" class="org.red5.server.Context" autowire="byType">
	    <property name="scopeResolver" ref="red5.scopeResolver" />
	    <property name="clientRegistry" ref="authClientRegistry" /> 
	    <property name="serviceInvoker" ref="global.serviceInvoker" />
	    <property name="mappingStrategy" ref="global.mappingStrategy" />
	</bean>

	<bean id="web.scope" class="org.red5.server.WebScope" init-method="register">
		<property name="server" ref="red5.server" />
		<property name="parent" ref="global.scope" />
		<property name="context" ref="web.context" />
		<property name="handler" ref="web.handler" />
		<property name="contextPath" value="${webapp.contextPath}" />
		<property name="virtualHosts" value="${webapp.virtualHosts}" />
	</bean>

	<bean id="web.handler" class="org.red5.webapps.admin.Application" />
		
</beans>
